nepali_unicode_converter/__init__.py
nepali_unicode_converter/convert.py
nepali_unicode_converter/mappings.py
nepali_unicode_converter/word_maps.txt
nepali_unicode_converter-1.0.3.dist-info/METADATA
nepali_unicode_converter-1.0.3.dist-info/WHEEL
nepali_unicode_converter-1.0.3.dist-info/top_level.txt
nepali_unicode_converter-1.0.3.dist-info/RECORD
