Metadata-Version: 2.1
Name: nepali-unicode-converter
Version: 1.0.3
Summary: Roman text to unicode converter
Home-page: https://github.com/bewakes/nepali-unicode-converter
Author: Bibek Pandey
Author-email: bewakepandey@gmail.com
License: UNKNOWN
Platform: UNKNOWN
